PyRational/models/ADG.py
PyRational/models/AbstractModels.py
PyRational/models/__init__.py
PyRational/special/gambles.py
PyRational-0.0.4.dist-info/METADATA
PyRational-0.0.4.dist-info/RECORD
PyRational-0.0.4.dist-info/WHEEL
PyRational-0.0.4.dist-info/top_level.txt
