Metadata-Version: 2.1
Name: PyRational
Version: 0.0.4
Summary: A package for rational modelling and dual probabilisitc programming
Home-page: https://github.com/PyRational/PyRational
Author: Alessio Benavoli
Author-email: benavoli@gmail.com
License: UNKNOWN
Platform: UNKNOWN
Classifier: Programming Language :: Python :: 3
Classifier: License :: OSI Approved :: BSD License
Classifier: Operating System :: OS Independent
Requires-Dist: numpy (>=1.7)
Requires-Dist: scipy (>=0.16)
Requires-Dist: SymPy (>=1.2)
